Workbook

Sheet Resultado
A1: Algo Nuestro · Cuánto sale hacer una cartera
A2: Esta hoja no se toca: se calcula sola con las otras.
B4: Bandolera Potra | C4: Matera Criolla | D4: Cartera Gauchita
A5: Materiales, taller, trenzado y packaging | B5: =SUMIFS('Costos por cartera'!$G$6:$G$45,'Costos por cartera'!C$6:C$45,"x") | C5: =SUMIFS('Costos por cartera'!$G$6:$G$45,'Costos por cartera'!D$6:D$45,"x") | D5: =SUMIFS('Costos por cartera'!$G$6:$G$45,'Costos por cartera'!E$6:E$45,"x")
A6: + Muestras y moldes (mientras se recuperan) | B6: =IF(Supuestos!$B$5>0,SUM('Gastos de arranque'!F$6:F$25)/Supuestos!$B$5,0) | C6: =IF(Supuestos!$B$5>0,SUM('Gastos de arranque'!G$6:G$25)/Supuestos!$B$5,0) | D6: =IF(Supuestos!$B$5>0,SUM('Gastos de arranque'!H$6:H$25)/Supuestos!$B$5,0)
A7: + Gastos fijos del mes (por cartera vendida) | B7: =IF(Supuestos!$B$6>0,SUM('Gastos fijos'!$B$6:$B$15)/Supuestos!$B$6,0) | C7: =IF(Supuestos!$B$6>0,SUM('Gastos fijos'!$B$6:$B$15)/Supuestos!$B$6,0) | D7: =IF(Supuestos!$B$6>0,SUM('Gastos fijos'!$B$6:$B$15)/Supuestos!$B$6,0)
A8: Costo con TODO incluido | B8: =SUM(B5:B7) | C8: =SUM(C5:C7) | D8: =SUM(D5:D7)
A10: Precio de venta | B10: Bandolera Potra | C10: Matera Criolla | D10: Cartera Gauchita
A11: Precio sugerido = costo ÷ (1 − margen − comisiones) | B11: =IF(1-Supuestos!$B$7-Supuestos!$B$12<=0,0,B8/(1-Supuestos!$B$7-Supuestos!$B$12)) | C11: =IF(1-Supuestos!$B$7-Supuestos!$B$12<=0,0,C8/(1-Supuestos!$B$7-Supuestos!$B$12)) | D11: =IF(1-Supuestos!$B$7-Supuestos!$B$12<=0,0,D8/(1-Supuestos!$B$7-Supuestos!$B$12))
A12: Precio redondeado | B12: =IF(Supuestos!$B$11>0,CEILING(B11,Supuestos!$B$11),B11) | C12: =IF(Supuestos!$B$11>0,CEILING(C11,Supuestos!$B$11),C11) | D12: =IF(Supuestos!$B$11>0,CEILING(D11,Supuestos!$B$11),D11)
A13: − Comisiones e impuestos | B13: =B12*Supuestos!$B$12 | C13: =C12*Supuestos!$B$12 | D13: =D12*Supuestos!$B$12
A14: Te queda por cartera | B14: =B12-B13-B8 | C14: =C12-C13-C8 | D14: =D12-D13-D8
A15: Margen real | B15: =IF(B12=0,0,B14/B12) | C15: =IF(C12=0,0,C14/C12) | D15: =IF(D12=0,0,D14/D12)
A17: Para tener en cuenta
A18: Costos cargados sin precio (filas amarillas vacías) | B18: =COUNTIFS('Costos por cartera'!$A$6:$A$45,"<>",'Costos por cartera'!$B$6:$B$45,"") | C18: Mientras haya costos sin precio, el costo real es más alto.
A19: Invertido en muestras y moldes | B19: =SUM('Gastos de arranque'!$B$6:$B$25)
A20: Plata puesta en compras (bolsas, etc.) | B20: =SUM('Costos por cartera'!$I$6:$I$45)
A21: Gastos fijos por mes | B21: =SUM('Gastos fijos'!$B$6:$B$15)
A22: Las muestras y moldes se dejan de cobrar después de las primeras carteras de cada modelo (hoja Supuestos): ahí el costo baja.

Sheet Supuestos
A1: Supuestos
A2: Celdas amarillas: las cambiás vos. Los números de ejemplo vienen de lo que pasó Loli; las comisiones están pendientes.
A4: Dato | B4: Valor | C4: De dónde sale
A5: Recuperar muestras y moldes en … carteras de cada modelo | B5: 10 | C5: Decisión de Loli: 10 de cada una (30 en total).
A6: Carteras que pensás vender por mes (todas juntas) | B6: 20 | C6: SUPUESTO de ejemplo: cambialo por tu estimación.
A7: Margen que querés quedarte (% del precio de venta) | B7: 0.5 | C7: Margen sobre el precio, no sobre el costo.
A8: Comisión Tiendanube por venta | B8: 0 | C8: PENDIENTE: según tu plan.
A9: Comisión Mercado Pago (el medio de pago más caro que ofrezcas) | B9: 0 | C9: PENDIENTE: ver la tabla de costos de Mercado Pago.
A10: IVA sobre las comisiones | B10: 0.21 | C10: Como monotributista no lo recuperás. Poné 0% si no aplica.
A11: Redondear el precio a (para arriba) | B11: 1000 | C11: Poné 0 para no redondear.
A12: Comisiones e impuestos por venta, en total | B12: =(B8+B9)*(1+B10) | C12: Se calcula solo: (Tiendanube + Mercado Pago) × (1 + IVA)

Sheet Costos por cartera
A1: Costos por cartera
A2: Una fila por cada cosa que usa una cartera: cuero, taller, trenzado, herrajes, bolsas, envío.
A3: Poné una x en las carteras que la usan. Amarillo = lo completás vos. Las columnas blancas se calculan solas.
A4: Si compraste por cantidad, poné el precio de UNA unidad y cuántas compraste: a la cartera se le cobra solo lo que usa.
A5: Concepto | B5: Precio por unidad | C5: Potra | D5: Criolla | E5: Gauchita | F5: Cuántas usa cada cartera | G5: Costo por cartera | H5: Cuántas compraste | I5: Total pagado | J5: Nota
A6: Trenzado plano | B6: 16000 | E6: x | F6: 1 | G6: =IF(B6="","",B6*IF(F6="",1,F6)) | I6: =IF(OR(B6="",H6=""),"",B6*H6) | J6: Precio por cartera.
A7: Trenzado tubular | B7: 19000 | D7: x | F7: 1 | G7: =IF(B7="","",B7*IF(F7="",1,F7)) | I7: =IF(OR(B7="",H7=""),"",B7*H7) | J7: Precio por cartera.
A8: Bolsa de lienzo chica | B8: 2600 | C8: x | F8: 1 | G8: =IF(B8="","",B8*IF(F8="",1,F8)) | H8: 30 | I8: =IF(OR(B8="",H8=""),"",B8*H8) | J8: Precio final.
A9: Bolsa de cartulina chica | B9: 3670 | C9: x | F9: 1 | G9: =IF(B9="","",B9*IF(F9="",1,F9)) | H9: 25 | I9: =IF(OR(B9="",H9=""),"",B9*H9) | J9: Precio final.
A10: Bolsa e-commerce chica | B10: 133 | C10: x | F10: 1 | G10: =IF(B10="","",B10*IF(F10="",1,F10)) | H10: 100 | I10: =IF(OR(B10="",H10=""),"",B10*H10) | J10: Precio final.
A11: Bolsa de lienzo grande | B11: 4500 | D11: x | E11: x | F11: 1 | G11: =IF(B11="","",B11*IF(F11="",1,F11)) | H11: 30 | I11: =IF(OR(B11="",H11=""),"",B11*H11) | J11: Precio final. Se usa en Criolla y Gauchita.
A12: Bolsa de cartulina grande | B12: 4705 | D12: x | E12: x | F12: 1 | G12: =IF(B12="","",B12*IF(F12="",1,F12)) | H12: 50 | I12: =IF(OR(B12="",H12=""),"",B12*H12) | J12: Precio final. Se usa en Criolla y Gauchita.
A13: Bolsa e-commerce grande | B13: 305 | D13: x | E13: x | F13: 1 | G13: =IF(B13="","",B13*IF(F13="",1,F13)) | H13: 100 | I13: =IF(OR(B13="",H13=""),"",B13*H13) | J13: Precio final. Se usa en Criolla y Gauchita.
A14: Cuero de producción — Potra | C14: x | F14: 1 | G14: =IF(B14="","",B14*IF(F14="",1,F14)) | I14: =IF(OR(B14="",H14=""),"",B14*H14) | J14: FALTA: precio de la chapa ÷ carteras que salen de una chapa.
A15: Cuero de producción — Criolla | D15: x | F15: 1 | G15: =IF(B15="","",B15*IF(F15="",1,F15)) | I15: =IF(OR(B15="",H15=""),"",B15*H15) | J15: FALTA
A16: Cuero de producción — Gauchita | E16: x | F16: 1 | G16: =IF(B16="","",B16*IF(F16="",1,F16)) | I16: =IF(OR(B16="",H16=""),"",B16*H16) | J16: FALTA
A17: Taller (mano de obra de producción) — Potra | C17: x | F17: 1 | G17: =IF(B17="","",B17*IF(F17="",1,F17)) | I17: =IF(OR(B17="",H17=""),"",B17*H17) | J17: FALTA: lo que cobra el taller por cartera (no la muestra).
A18: Taller (mano de obra de producción) — Criolla | D18: x | F18: 1 | G18: =IF(B18="","",B18*IF(F18="",1,F18)) | I18: =IF(OR(B18="",H18=""),"",B18*H18) | J18: FALTA
A19: Taller (mano de obra de producción) — Gauchita | E19: x | F19: 1 | G19: =IF(B19="","",B19*IF(F19="",1,F19)) | I19: =IF(OR(B19="",H19=""),"",B19*H19) | J19: FALTA
A20: Herrajes, cierres, forro, hilo — Potra | C20: x | F20: 1 | G20: =IF(B20="","",B20*IF(F20="",1,F20)) | I20: =IF(OR(B20="",H20=""),"",B20*H20) | J20: FALTA: broche imán, cierres, hebilla, microfibra, hilo.
A21: Herrajes, cierres, forro, hilo — Criolla | D21: x | F21: 1 | G21: =IF(B21="","",B21*IF(F21="",1,F21)) | I21: =IF(OR(B21="",H21=""),"",B21*H21) | J21: FALTA
A22: Herrajes, cierres, forro, hilo — Gauchita | E22: x | F22: 1 | G22: =IF(B22="","",B22*IF(F22="",1,F22)) | I22: =IF(OR(B22="",H22=""),"",B22*H22) | J22: FALTA
G23: =IF(B23="","",B23*IF(F23="",1,F23)) | I23: =IF(OR(B23="",H23=""),"",B23*H23)
G24: =IF(B24="","",B24*IF(F24="",1,F24)) | I24: =IF(OR(B24="",H24=""),"",B24*H24)
G25: =IF(B25="","",B25*IF(F25="",1,F25)) | I25: =IF(OR(B25="",H25=""),"",B25*H25)
G26: =IF(B26="","",B26*IF(F26="",1,F26)) | I26: =IF(OR(B26="",H26=""),"",B26*H26)
G27: =IF(B27="","",B27*IF(F27="",1,F27)) | I27: =IF(OR(B27="",H27=""),"",B27*H27)
G28: =IF(B28="","",B28*IF(F28="",1,F28)) | I28: =IF(OR(B28="",H28=""),"",B28*H28)
G29: =IF(B29="","",B29*IF(F29="",1,F29)) | I29: =IF(OR(B29="",H29=""),"",B29*H29)
G30: =IF(B30="","",B30*IF(F30="",1,F30)) | I30: =IF(OR(B30="",H30=""),"",B30*H30)
G31: =IF(B31="","",B31*IF(F31="",1,F31)) | I31: =IF(OR(B31="",H31=""),"",B31*H31)
G32: =IF(B32="","",B32*IF(F32="",1,F32)) | I32: =IF(OR(B32="",H32=""),"",B32*H32)
G33: =IF(B33="","",B33*IF(F33="",1,F33)) | I33: =IF(OR(B33="",H33=""),"",B33*H33)
G34: =IF(B34="","",B34*IF(F34="",1,F34)) | I34: =IF(OR(B34="",H34=""),"",B34*H34)
... G45: =IF(B45="","",B45*IF(F45="",1,F45)) | I45: =IF(OR(B45="",H45=""),"",B45*H45)

Sheet Gastos de arranque
A1: Gastos de arranque (se pagan una sola vez)
A2: Muestras, moldes, envíos de muestras. Poné una x en los modelos a los que corresponde: se reparte en partes iguales entre ellos.
A3: Después se divide por las carteras en que lo querés recuperar (hoja Supuestos).
A5: Concepto | B5: Monto | C5: Potra | D5: Criolla | E5: Gauchita | F5: Parte Potra | G5: Parte Criolla | H5: Parte Gauchita | I5: Nota
A6: 2 chapas de cuero para las muestras (≈1,6 m² c/u) | B6: 95000 | C6: x | D6: x | E6: x | F6: =IF(OR($B6="",C6<>"x"),0,$B6/COUNTIF($C6:$E6,"x")) | G6: =IF(OR($B6="",D6<>"x"),0,$B6/COUNTIF($C6:$E6,"x")) | H6: =IF(OR($B6="",E6<>"x"),0,$B6/COUNTIF($C6:$E6,"x")) | I6: Con eso se hicieron las 3 muestras.
A7: Muestra en friselina (las 3) | B7: 100000 | C7: x | D7: x | E7: x | F7: =IF(OR($B7="",C7<>"x"),0,$B7/COUNTIF($C7:$E7,"x")) | G7: =IF(OR($B7="",D7<>"x"),0,$B7/COUNTIF($C7:$E7,"x")) | H7: =IF(OR($B7="",E7<>"x"),0,$B7/COUNTIF($C7:$E7,"x"))
A8: Envío muestras friselina | B8: 40000 | C8: x | D8: x | E8: x | F8: =IF(OR($B8="",C8<>"x"),0,$B8/COUNTIF($C8:$E8,"x")) | G8: =IF(OR($B8="",D8<>"x"),0,$B8/COUNTIF($C8:$E8,"x")) | H8: =IF(OR($B8="",E8<>"x"),0,$B8/COUNTIF($C8:$E8,"x")) | I8: Se cobra a las 3 por igual.
A9: Envío trenzador | B9: 30000 | D9: x | E9: x | F9: =IF(OR($B9="",C9<>"x"),0,$B9/COUNTIF($C9:$E9,"x")) | G9: =IF(OR($B9="",D9<>"x"),0,$B9/COUNTIF($C9:$E9,"x")) | H9: =IF(OR($B9="",E9<>"x"),0,$B9/COUNTIF($C9:$E9,"x")) | I9: Solo a las que llevan trenzado.
A10: Molde / muestra: mano de obra cuero y molde papel — Potra | B10: 50000 | C10: x | F10: =IF(OR($B10="",C10<>"x"),0,$B10/COUNTIF($C10:$E10,"x")) | G10: =IF(OR($B10="",D10<>"x"),0,$B10/COUNTIF($C10:$E10,"x")) | H10: =IF(OR($B10="",E10<>"x"),0,$B10/COUNTIF($C10:$E10,"x"))
A11: Molde / muestra: mano de obra cuero y molde papel — Criolla | B11: 50000 | D11: x | F11: =IF(OR($B11="",C11<>"x"),0,$B11/COUNTIF($C11:$E11,"x")) | G11: =IF(OR($B11="",D11<>"x"),0,$B11/COUNTIF($C11:$E11,"x")) | H11: =IF(OR($B11="",E11<>"x"),0,$B11/COUNTIF($C11:$E11,"x"))
A12: Molde / muestra: mano de obra cuero y molde papel — Gauchita | B12: 50000 | E12: x | F12: =IF(OR($B12="",C12<>"x"),0,$B12/COUNTIF($C12:$E12,"x")) | G12: =IF(OR($B12="",D12<>"x"),0,$B12/COUNTIF($C12:$E12,"x")) | H12: =IF(OR($B12="",E12<>"x"),0,$B12/COUNTIF($C12:$E12,"x"))
F13: =IF(OR($B13="",C13<>"x"),0,$B13/COUNTIF($C13:$E13,"x")) | G13: =IF(OR($B13="",D13<>"x"),0,$B13/COUNTIF($C13:$E13,"x")) | H13: =IF(OR($B13="",E13<>"x"),0,$B13/COUNTIF($C13:$E13,"x"))
F14: =IF(OR($B14="",C14<>"x"),0,$B14/COUNTIF($C14:$E14,"x")) | G14: =IF(OR($B14="",D14<>"x"),0,$B14/COUNTIF($C14:$E14,"x")) | H14: =IF(OR($B14="",E14<>"x"),0,$B14/COUNTIF($C14:$E14,"x"))
F15: =IF(OR($B15="",C15<>"x"),0,$B15/COUNTIF($C15:$E15,"x")) | G15: =IF(OR($B15="",D15<>"x"),0,$B15/COUNTIF($C15:$E15,"x")) | H15: =IF(OR($B15="",E15<>"x"),0,$B15/COUNTIF($C15:$E15,"x"))
F16: =IF(OR($B16="",C16<>"x"),0,$B16/COUNTIF($C16:$E16,"x")) | G16: =IF(OR($B16="",D16<>"x"),0,$B16/COUNTIF($C16:$E16,"x")) | H16: =IF(OR($B16="",E16<>"x"),0,$B16/COUNTIF($C16:$E16,"x"))
F17: =IF(OR($B17="",C17<>"x"),0,$B17/COUNTIF($C17:$E17,"x")) | G17: =IF(OR($B17="",D17<>"x"),0,$B17/COUNTIF($C17:$E17,"x")) | H17: =IF(OR($B17="",E17<>"x"),0,$B17/COUNTIF($C17:$E17,"x"))
F18: =IF(OR($B18="",C18<>"x"),0,$B18/COUNTIF($C18:$E18,"x")) | G18: =IF(OR($B18="",D18<>"x"),0,$B18/COUNTIF($C18:$E18,"x")) | H18: =IF(OR($B18="",E18<>"x"),0,$B18/COUNTIF($C18:$E18,"x"))
F19: =IF(OR($B19="",C19<>"x"),0,$B19/COUNTIF($C19:$E19,"x")) | G19: =IF(OR($B19="",D19<>"x"),0,$B19/COUNTIF($C19:$E19,"x")) | H19: =IF(OR($B19="",E19<>"x"),0,$B19/COUNTIF($C19:$E19,"x"))
F20: =IF(OR($B20="",C20<>"x"),0,$B20/COUNTIF($C20:$E20,"x")) | G20: =IF(OR($B20="",D20<>"x"),0,$B20/COUNTIF($C20:$E20,"x")) | H20: =IF(OR($B20="",E20<>"x"),0,$B20/COUNTIF($C20:$E20,"x"))
F21: =IF(OR($B21="",C21<>"x"),0,$B21/COUNTIF($C21:$E21,"x")) | G21: =IF(OR($B21="",D21<>"x"),0,$B21/COUNTIF($C21:$E21,"x")) | H21: =IF(OR($B21="",E21<>"x"),0,$B21/COUNTIF($C21:$E21,"x"))
F22: =IF(OR($B22="",C22<>"x"),0,$B22/COUNTIF($C22:$E22,"x")) | G22: =IF(OR($B22="",D22<>"x"),0,$B22/COUNTIF($C22:$E22,"x")) | H22: =IF(OR($B22="",E22<>"x"),0,$B22/COUNTIF($C22:$E22,"x"))
F23: =IF(OR($B23="",C23<>"x"),0,$B23/COUNTIF($C23:$E23,"x")) | G23: =IF(OR($B23="",D23<>"x"),0,$B23/COUNTIF($C23:$E23,"x")) | H23: =IF(OR($B23="",E23<>"x"),0,$B23/COUNTIF($C23:$E23,"x"))
F24: =IF(OR($B24="",C24<>"x"),0,$B24/COUNTIF($C24:$E24,"x")) | G24: =IF(OR($B24="",D24<>"x"),0,$B24/COUNTIF($C24:$E24,"x")) | H24: =IF(OR($B24="",E24<>"x"),0,$B24/COUNTIF($C24:$E24,"x"))
F25: =IF(OR($B25="",C25<>"x"),0,$B25/COUNTIF($C25:$E25,"x")) | G25: =IF(OR($B25="",D25<>"x"),0,$B25/COUNTIF($C25:$E25,"x")) | H25: =IF(OR($B25="",E25<>"x"),0,$B25/COUNTIF($C25:$E25,"x"))

Sheet Gastos fijos
A1: Gastos fijos del mes
A2: Lo que pagás todos los meses. Se reparte entre las carteras que vendés por mes (hoja Supuestos).
A5: Concepto | B5: Por mes | C5: Nota
A6: Monotributo | B6: 10000
A7: Plan Tiendanube | B7: 28000
