Workbook

Sheet Por cartera
A1: Algo Nuestro · Cuánto sale hacer una cartera
A2: Todo se calcula con las otras hojas. Las filas amarillas son costos que todavía faltan: completalos acá.
A4: Concepto | B4: Bandolera Potra | C4: Matera Criolla | D4: Cartera Gauchita
A5: Trenzado | B5: 0 | C5: =Compras!$F$6 | D5: =Compras!$F$5
A6: Bolsa de lienzo | B6: =Compras!$F$7 | C6: =Compras!$F$10 | D6: =Compras!$F$10
A7: Bolsa de cartulina | B7: =Compras!$F$8 | C7: =Compras!$F$11 | D7: =Compras!$F$11
A8: Bolsa e-commerce | B8: =Compras!$F$9 | C8: =Compras!$F$12 | D8: =Compras!$F$12
A9: Cuero de producción (por cartera)
A10: Mano de obra del taller (producción)
A11: Herrajes, cierres, forro, hilo
A12: Envío al cliente (si lo pagás vos)
A13: Costo por cartera (materiales, trenzado, packaging) | B13: =SUM(B5:B12) | C13: =SUM(C5:C12) | D13: =SUM(D5:D12)
A14: + Muestras y moldes (mientras se recuperan) | B14: ='Muestras y moldes'!$F$13 | C14: ='Muestras y moldes'!$G$13 | D14: ='Muestras y moldes'!$H$13
A15: + Gastos fijos del mes (monotributo, Tiendanube) | B15: ='Fijos del mes'!$B$9 | C15: ='Fijos del mes'!$B$9 | D15: ='Fijos del mes'!$B$9
A16: Costo con TODO incluido | B16: =B13+B14+B15 | C16: =C13+C14+C15 | D16: =D13+D14+D15
A18: Precio sugerido | B18: Bandolera Potra | C18: Matera Criolla | D18: Cartera Gauchita
A19: Precio = Costo ÷ (1 − margen − comisiones) | B19: =IF(1-Supuestos!$B$7-Supuestos!$B$12<=0,"",B16/(1-Supuestos!$B$7-Supuestos!$B$12)) | C19: =IF(1-Supuestos!$B$7-Supuestos!$B$12<=0,"",C16/(1-Supuestos!$B$7-Supuestos!$B$12)) | D19: =IF(1-Supuestos!$B$7-Supuestos!$B$12<=0,"",D16/(1-Supuestos!$B$7-Supuestos!$B$12))
A20: Precio redondeado (para arriba) | B20: =IF(B19="","",IF(Supuestos!$B$11>0,CEILING(B19,Supuestos!$B$11),B19)) | C20: =IF(C19="","",IF(Supuestos!$B$11>0,CEILING(C19,Supuestos!$B$11),C19)) | D20: =IF(D19="","",IF(Supuestos!$B$11>0,CEILING(D19,Supuestos!$B$11),D19))
A21: − Comisiones e IVA de comisiones | B21: =IF(B20="","",B20*Supuestos!$B$12) | C21: =IF(C20="","",C20*Supuestos!$B$12) | D21: =IF(D20="","",D20*Supuestos!$B$12)
A22: Te queda por cartera | B22: =IF(B20="","",B20-B21-B16) | C22: =IF(C20="","",C20-C21-C16) | D22: =IF(D20="","",D20-D21-D16)
A23: Margen real | B23: =IF(B20="","",B22/B20) | C23: =IF(C20="","",C22/C20) | D23: =IF(D20="","",D22/D20)
A25: Ojo: mientras las filas amarillas estén vacías, el costo va a dar más bajo de lo real (falta el cuero, el taller y los herrajes de producción).
A26: Después de las primeras carteras de cada modelo (Supuestos), las muestras y moldes ya están pagos y el costo baja.

Sheet Supuestos
A1: Algo Nuestro · Supuestos
A2: Celdas amarillas con número azul: las completás o cambiás vos. Todo lo demás se calcula solo.
A4: Dato | B4: Valor | C4: Nota
A5: Recuperar muestras y moldes en … carteras de cada modelo | B5: 10 | C5: Con 10: se recuperan con las primeras 10 de cada modelo (30 en total).
A6: Carteras que pensás vender por mes (todas) | B6: 20 | C6: SUPUESTO para el ejemplo: cambialo por tu estimación.
A7: Margen que querés quedarte (% del precio) | B7: 0.5 | C7: El margen es sobre el precio de venta.
A8: Comisión Tiendanube por venta | B8: 0 | C8: PENDIENTE: completar según tu plan.
A9: Comisión Mercado Pago (el medio más caro que ofrezcas) | B9: 0 | C9: PENDIENTE: ver costos de Mercado Pago.
A10: IVA sobre comisiones | B10: 0.21 | C10: Como monotributista no lo recuperás. Poné 0% si no aplica.
A11: Redondear precio a | B11: 1000 | C11: Se redondea para arriba.
A12: Comisiones e impuestos totales | B12: =(B8+B9)*(1+B10) | C12: (Tiendanube + Mercado Pago) × (1 + IVA)

Sheet Compras
A1: Lo que usa cada cartera
A2: Precio por unidad × cuántas usa cada cartera. Lo que compraste de más queda de stock y no se le cobra a nadie.
A4: Ítem | B4: Para | C4: Precio por unidad | D4: Compraste | E4: Usa cada cartera | F4: Costo por cartera | G4: Total pagado | H4: Alcanza para (carteras)
A5: Trenzado plano | B5: Gauchita | C5: 16000 | E5: 1 | F5: =C5*E5 | G5: =IF(D5="","",C5*D5) | H5: =IF(D5="","",D5/E5)
A6: Trenzado tubular | B6: Criolla | C6: 19000 | E6: 1 | F6: =C6*E6 | G6: =IF(D6="","",C6*D6) | H6: =IF(D6="","",D6/E6)
A7: Bolsa lienzo chica | B7: Potra | C7: 2600 | D7: 30 | E7: 1 | F7: =C7*E7 | G7: =IF(D7="","",C7*D7) | H7: =IF(D7="","",D7/E7)
A8: Bolsa cartulina chica | B8: Potra | C8: 3670 | D8: 25 | E8: 1 | F8: =C8*E8 | G8: =IF(D8="","",C8*D8) | H8: =IF(D8="","",D8/E8)
A9: Bolsa e-commerce chica | B9: Potra | C9: 133 | D9: 100 | E9: 1 | F9: =C9*E9 | G9: =IF(D9="","",C9*D9) | H9: =IF(D9="","",D9/E9)
A10: Bolsa lienzo grande | B10: Gauchita y Criolla | C10: 4500 | D10: 30 | E10: 1 | F10: =C10*E10 | G10: =IF(D10="","",C10*D10) | H10: =IF(D10="","",D10/E10)
A11: Bolsa cartulina grande | B11: Gauchita y Criolla | C11: 4705 | D11: 50 | E11: 1 | F11: =C11*E11 | G11: =IF(D11="","",C11*D11) | H11: =IF(D11="","",D11/E11)
A12: Bolsa e-commerce grande | B12: Gauchita y Criolla | C12: 305 | D12: 100 | E12: 1 | F12: =C12*E12 | G12: =IF(D12="","",C12*D12) | H12: =IF(D12="","",D12/E12)
A13: Total pagado en compras | G13: =SUM(G5:G12)
A15: Precios de Loli. Si alguno era sin IVA, multiplicalo por 1,21 en la columna C.

Sheet Muestras y moldes
A1: Muestras y moldes (se pagan una sola vez)
A2: Poné 1 en cada modelo al que corresponde el gasto. Se reparte en partes iguales entre esos modelos.
A4: Gasto | B4: Monto | C4: Potra | D4: Criolla | E4: Gauchita | F4: Parte Potra | G4: Parte Criolla | H4: Parte Gauchita
A5: 2 chapas de cuero (≈1,6 m² c/u) para las muestras | B5: 95000 | C5: 1 | D5: 1 | E5: 1 | F5: =IF(SUM($C5:$E5)=0,0,$B5*C5/SUM($C5:$E5)) | G5: =IF(SUM($C5:$E5)=0,0,$B5*D5/SUM($C5:$E5)) | H5: =IF(SUM($C5:$E5)=0,0,$B5*E5/SUM($C5:$E5))
A6: Muestra en friselina (las 3) | B6: 100000 | C6: 1 | D6: 1 | E6: 1 | F6: =IF(SUM($C6:$E6)=0,0,$B6*C6/SUM($C6:$E6)) | G6: =IF(SUM($C6:$E6)=0,0,$B6*D6/SUM($C6:$E6)) | H6: =IF(SUM($C6:$E6)=0,0,$B6*E6/SUM($C6:$E6))
A7: Envío muestras friselina | B7: 40000 | C7: 1 | D7: 1 | E7: 1 | F7: =IF(SUM($C7:$E7)=0,0,$B7*C7/SUM($C7:$E7)) | G7: =IF(SUM($C7:$E7)=0,0,$B7*D7/SUM($C7:$E7)) | H7: =IF(SUM($C7:$E7)=0,0,$B7*E7/SUM($C7:$E7))
A8: Envío trenzador (solo las trenzadas) | B8: 30000 | C8: 0 | D8: 1 | E8: 1 | F8: =IF(SUM($C8:$E8)=0,0,$B8*C8/SUM($C8:$E8)) | G8: =IF(SUM($C8:$E8)=0,0,$B8*D8/SUM($C8:$E8)) | H8: =IF(SUM($C8:$E8)=0,0,$B8*E8/SUM($C8:$E8))
A9: Molde / muestra: mano de obra cuero y molde papel — Potra | B9: 50000 | C9: 1 | D9: 0 | E9: 0 | F9: =IF(SUM($C9:$E9)=0,0,$B9*C9/SUM($C9:$E9)) | G9: =IF(SUM($C9:$E9)=0,0,$B9*D9/SUM($C9:$E9)) | H9: =IF(SUM($C9:$E9)=0,0,$B9*E9/SUM($C9:$E9))
A10: Molde / muestra: mano de obra cuero y molde papel — Criolla | B10: 50000 | C10: 0 | D10: 1 | E10: 0 | F10: =IF(SUM($C10:$E10)=0,0,$B10*C10/SUM($C10:$E10)) | G10: =IF(SUM($C10:$E10)=0,0,$B10*D10/SUM($C10:$E10)) | H10: =IF(SUM($C10:$E10)=0,0,$B10*E10/SUM($C10:$E10))
A11: Molde / muestra: mano de obra cuero y molde papel — Gauchita | B11: 50000 | C11: 0 | D11: 0 | E11: 1 | F11: =IF(SUM($C11:$E11)=0,0,$B11*C11/SUM($C11:$E11)) | G11: =IF(SUM($C11:$E11)=0,0,$B11*D11/SUM($C11:$E11)) | H11: =IF(SUM($C11:$E11)=0,0,$B11*E11/SUM($C11:$E11))
A12: Total por modelo | B12: =SUM(B5:B11) | F12: =SUM(F5:F11) | G12: =SUM(G5:G11) | H12: =SUM(H5:H11)
A13: Por cartera (÷ carteras de cada modelo en Supuestos) | F13: =F12/Supuestos!$B$5 | G13: =G12/Supuestos!$B$5 | H13: =H12/Supuestos!$B$5
A14: Control: la suma de las partes tiene que dar el total | B14: =IF(ROUND(SUM(F12:H12)-B12,0)=0,"OK","Revisar")

Sheet Fijos del mes
A1: Gastos fijos del mes
A2: Se reparten entre las carteras que vendés por mes (Supuestos).
A4: Gasto | B4: Por mes | C4: Nota
A5: Monotributo | B5: 10000
A6: Plan Tiendanube | B6: 28000
A7: Otro (si aparece) | B7: 0
A8: Total por mes | B8: =SUM(B5:B7)
A9: Por cartera vendida | B9: =IF(Supuestos!$B$6>0,B8/Supuestos!$B$6,0) | C9: =total por mes ÷ carteras que vendés por mes
